{
    "wallpaper": "/home/denis/.config/wpg/wallpapers/Boats_Thailand_Sea_Crag_Nature_8000x5224.jpg",
    "alpha": "100",

    "special": {
        "background": "#071104",
        "foreground": "#f5ffff",
        "cursor": "#f5ffff"
    },
    "colors": {
        "color0": "#071104",
        "color1": "#ACE0E9",
        "color2": "#B5C854",
        "color3": "#D7DAA3",
        "color4": "#ADB89B",
        "color5": "#4EB0B1",
        "color6": "#D8E1D4",
        "color7": "#dfeef1",
        "color8": "#163b0b",
        "color9": "#bfffff",
        "color10": "#f7ff5a",
        "color11": "#ffffbb",
        "color12": "#e6ffb3",
        "color13": "#54f5f6",
        "color14": "#f2ffde",
        "color15": "#f5ffff"
    }
}
